{
  "meta": {
    "competition_code": "CSL",
    "season": "2026",
    "updated_at": "2026-07-15T11:17:43+01:00"
  },
  "rows": [
    {
      "home_team": "Beijing Guoan",
      "away_team": "Liaoning Tieren",
      "match_time": "11:35",
      "home_spread": -1.5,
      "away_spread": 1.5,
      "home_odds": 2.03,
      "away_odds": 1.82,
      "home_ah_ev": 0.2598417112121969,
      "away_ah_ev": -0.3095132583281766,
      "open_home_spread": -1.25,
      "open_away_spread": 1.25,
      "open_home_odds": 1.87,
      "open_away_odds": 1.93,
      "open_home_ah_ev": 0.2619363797234327,
      "open_away_ah_ev": -0.3620756029311709,
      "open_last_update": "2026-07-11T08:42:52Z",
      "last_update": "2026-07-15T10:17:16Z",
      "fetched_at": "2026-07-15T10:17:41Z"
    },
    {
      "home_team": "Henan Songshan Longmen",
      "away_team": "Qingdao Hainiu",
      "match_time": "11:35",
      "home_spread": -1,
      "away_spread": 1,
      "home_odds": 1.91,
      "away_odds": 1.93,
      "home_ah_ev": -0.0491344349938994,
      "away_ah_ev": -0.0089217720321233,
      "open_home_spread": -1,
      "open_away_spread": 1,
      "open_home_odds": 1.88,
      "open_away_odds": 1.96,
      "open_home_ah_ev": -0.0597948377088864,
      "open_away_ah_ev": 0.0022532274883317,
      "open_last_update": "2026-07-14T13:41:06Z",
      "last_update": "2026-07-15T10:17:16Z",
      "fetched_at": "2026-07-15T10:17:41Z"
    },
    {
      "home_team": "Yunnan Yukun",
      "away_team": "Shanghai Port",
      "match_time": "12:00",
      "home_spread": 0,
      "away_spread": 0,
      "home_odds": 1.95,
      "away_odds": 1.88,
      "home_ah_ev": -0.0914184751071659,
      "away_ah_ev": 0.0270667287204722,
      "open_home_spread": 0,
      "open_away_spread": 0,
      "open_home_odds": 1.85,
      "open_away_odds": 1.98,
      "open_home_ah_ev": -0.1239681881399913,
      "open_away_ah_ev": 0.067130803612373,
      "open_last_update": "2026-07-12T11:47:09Z",
      "last_update": "2026-07-15T10:17:16Z",
      "fetched_at": "2026-07-15T10:17:41Z"
    },
    {
      "home_team": "Chongqing Tonglianglong",
      "away_team": "Zhejiang Professional",
      "match_time": "11:00",
      "home_spread": 0,
      "away_spread": 0,
      "home_odds": 2.06,
      "away_odds": 1.79,
      "home_ah_ev": -0.1145582476925678,
      "away_ah_ev": 0.0553577960276679,
      "open_home_spread": 0,
      "open_away_spread": 0,
      "open_home_odds": 1.98,
      "open_away_odds": 1.85,
      "open_home_ah_ev": -0.1318488846664722,
      "open_away_ah_ev": 0.075977347283476,
      "open_last_update": "2026-07-14T13:41:06Z",
      "last_update": "2026-07-15T10:17:16Z",
      "fetched_at": "2026-07-15T10:17:41Z"
    },
    {
      "home_team": "Qingdao West Coast",
      "away_team": "Chengdu Rongcheng",
      "match_time": "11:00",
      "home_spread": 0.75,
      "away_spread": -0.75,
      "home_odds": 1.85,
      "away_odds": 1.98,
      "home_ah_ev": 0.0281301946801973,
      "away_ah_ev": -0.1074842504873448,
      "open_home_spread": 0.75,
      "open_away_spread": -0.75,
      "open_home_odds": 1.83,
      "open_away_odds": 2.01,
      "open_home_ah_ev": 0.0185593372310055,
      "open_away_ah_ev": -0.0961253130800313,
      "open_last_update": "2026-07-11T13:49:00Z",
      "last_update": "2026-07-15T10:17:16Z",
      "fetched_at": "2026-07-15T10:17:41Z"
    },
    {
      "home_team": "Dalian Yingbo",
      "away_team": "Shandong Taishan",
      "match_time": "11:35",
      "home_spread": -0.25,
      "away_spread": 0.25,
      "home_odds": 1.97,
      "away_odds": 1.86,
      "home_ah_ev": -0.2420250610162429,
      "away_ah_ev": 0.1569239162314378,
      "open_home_spread": -0.25,
      "open_away_spread": 0.25,
      "open_home_odds": 1.89,
      "open_away_odds": 1.94,
      "open_home_ah_ev": -0.2667380338715052,
      "open_away_ah_ev": 0.2002575047823416,
      "open_last_update": "2026-07-12T11:47:09Z",
      "last_update": "2026-07-15T10:17:16Z",
      "fetched_at": "2026-07-15T10:17:41Z"
    },
    {
      "home_team": "Shanghai Shenhua",
      "away_team": "Tianjin Jinmen Tiger",
      "match_time": "11:35",
      "home_spread": -1.25,
      "away_spread": 1.25,
      "home_odds": 1.87,
      "away_odds": 1.97,
      "home_ah_ev": -0.1411462735134411,
      "away_ah_ev": 0.0770205292528599,
      "open_home_spread": -1,
      "open_away_spread": 1,
      "open_home_odds": 1.78,
      "open_away_odds": 2.04,
      "open_home_ah_ev": -0.0342916365089382,
      "open_away_ah_ev": -0.0367741613440777,
      "open_last_update": "2026-07-11T12:42:52Z",
      "last_update": "2026-07-15T10:17:16Z",
      "fetched_at": "2026-07-15T10:17:41Z"
    },
    {
      "home_team": "Wuhan Three Towns",
      "away_team": "Shenzhen Xinpengcheng",
      "match_time": "12:00",
      "home_spread": -0.25,
      "away_spread": 0.25,
      "home_odds": 1.83,
      "away_odds": 2.01,
      "home_ah_ev": 0.0899522330146666,
      "away_ah_ev": -0.1747759457833243,
      "open_home_spread": -0.25,
      "open_away_spread": 0.25,
      "open_home_odds": 1.84,
      "open_away_odds": 2,
      "open_home_ah_ev": 0.0951423499249022,
      "open_away_ah_ev": -0.1781842204886732,
      "open_last_update": "2026-07-11T13:49:00Z",
      "last_update": "2026-07-15T10:17:16Z",
      "fetched_at": "2026-07-15T10:17:41Z"
    }
  ]
}
